tf2_resnets/__init__.py
tf2_resnets/blocks.py
tf2_resnets/convolutions.py
tf2_resnets/imagenet_preprocessing.py
tf2_resnets/models.py
tf2_resnets/resnet.py
tf2_resnets/split_attention.py
tf2_resnets-0.3.0.dist-info/LICENSE
tf2_resnets-0.3.0.dist-info/METADATA
tf2_resnets-0.3.0.dist-info/WHEEL
tf2_resnets-0.3.0.dist-info/top_level.txt
tf2_resnets-0.3.0.dist-info/RECORD
