Metadata-Version: 2.1
Name: tf2-resnets
Version: 0.3.0
Summary: ResNet variations for TensorFlow.
Home-page: https://github.com/RichardXiao13/TensorFlow-ResNets
Author: Richard Xiao
Author-email: richard.xiao13@gmail.com
License: UNKNOWN
Platform: UNKNOWN
Classifier: Programming Language :: Python :: 3
Classifier: License :: OSI Approved :: MIT License
Classifier: Operating System :: OS Independent
Requires-Python: >=3.6
